LICENSE.txt
README.md
setup.py
udm_toolbox.egg-info/PKG-INFO
udm_toolbox.egg-info/SOURCES.txt
udm_toolbox.egg-info/dependency_links.txt
udm_toolbox.egg-info/top_level.txt
udmtoolbox/__init__.py
udmtoolbox/udm.py